vnpy_ksgold/__init__.py
vnpy_ksgold/api/__init__.py
vnpy_ksgold/api/ksgold_constant.py
vnpy_ksgold/api/libksgoldquotmarketdataapi.so
vnpy_ksgold/api/libksgoldtraderapi.so
vnpy_ksgold/api/generator/ksgold_md_header_define.h
vnpy_ksgold/api/generator/ksgold_md_header_function.h
vnpy_ksgold/api/generator/ksgold_md_header_on.h
vnpy_ksgold/api/generator/ksgold_md_header_process.h
vnpy_ksgold/api/generator/ksgold_md_source_function.cpp
vnpy_ksgold/api/generator/ksgold_md_source_module.cpp
vnpy_ksgold/api/generator/ksgold_md_source_on.cpp
vnpy_ksgold/api/generator/ksgold_md_source_process.cpp
vnpy_ksgold/api/generator/ksgold_md_source_switch.cpp
vnpy_ksgold/api/generator/ksgold_md_source_task.cpp
vnpy_ksgold/api/generator/ksgold_td_header_define.h
vnpy_ksgold/api/generator/ksgold_td_header_function.h
vnpy_ksgold/api/generator/ksgold_td_header_on.h
vnpy_ksgold/api/generator/ksgold_td_header_process.h
vnpy_ksgold/api/generator/ksgold_td_source_function.cpp
vnpy_ksgold/api/generator/ksgold_td_source_module.cpp
vnpy_ksgold/api/generator/ksgold_td_source_on.cpp
vnpy_ksgold/api/generator/ksgold_td_source_process.cpp
vnpy_ksgold/api/generator/ksgold_td_source_switch.cpp
vnpy_ksgold/api/generator/ksgold_td_source_task.cpp
vnpy_ksgold/api/include/ksgold/KSGoldError.h
vnpy_ksgold/api/include/ksgold/KSGoldQuotMarketDataApi.h
vnpy_ksgold/api/include/ksgold/KSGoldTradeDefine.h
vnpy_ksgold/api/include/ksgold/KSGoldTraderApi.h
vnpy_ksgold/api/include/ksgold/KSGoldUserApiDataTypeEx.h
vnpy_ksgold/api/include/ksgold/KSGoldUserApiStructEx.h
vnpy_ksgold/api/include/pybind11/attr.h
vnpy_ksgold/api/include/pybind11/buffer_info.h
vnpy_ksgold/api/include/pybind11/cast.h
vnpy_ksgold/api/include/pybind11/chrono.h
vnpy_ksgold/api/include/pybind11/common.h
vnpy_ksgold/api/include/pybind11/complex.h
vnpy_ksgold/api/include/pybind11/eigen.h
vnpy_ksgold/api/include/pybind11/embed.h
vnpy_ksgold/api/include/pybind11/eval.h
vnpy_ksgold/api/include/pybind11/functional.h
vnpy_ksgold-1.0.2.dist-info/LICENSE
vnpy_ksgold-1.0.2.dist-info/METADATA
vnpy_ksgold-1.0.2.dist-info/WHEEL
vnpy_ksgold-1.0.2.dist-info/top_level.txt
vnpy_ksgold-1.0.2.dist-info/RECORD
